Metadata-Version: 2.1
Name: pywellbeing
Version: 0.0.2
Summary: Computational models of human happiness, wellbeing, and motivation.
Home-page: https://github.com/pythoro/pywellbeing.git
Download-URL: https://github.com/pythoro/pywellbeing/archive/v0.0.1.zip
Author: Reuben Rusk
Author-email: pythoro@mindquip.com
Project-URL: Documentation, https://github.com/pythoro/pywellbeing.git
Project-URL: Source, https://github.com/pythoro/pywellbeing.git
Project-URL: Tracker, https://github.com/pythoro/pywellbeing/issues
Keywords: WELLBEING,HAPPINESS,COMPUTATIONAL MODEL,ADAPTIVE MOTIVATION,MOTIVATION
Classifier: Programming Language :: Python :: 3.6
Classifier: Programming Language :: Python :: 3.7
Classifier: Programming Language :: Python :: 3.8
Classifier: Programming Language :: Python :: 3.9
Classifier: Development Status :: 3 - Alpha
Classifier: License :: OSI Approved :: MIT License
Classifier: Operating System :: OS Independent
Classifier: Natural Language :: English
Classifier: Topic :: Software Development :: Libraries :: Python Modules
Classifier: Topic :: Scientific/Engineering
License-File: LICENSE
